zltask/__init__.py
zltask/create_long_ip_cfg.py
zltask/envconf.py
zltask/est_db.py
zltask/hawq.py
zltask/route.py
zltask-1.2.51.dist-info/METADATA
zltask-1.2.51.dist-info/WHEEL
zltask-1.2.51.dist-info/top_level.txt
zltask-1.2.51.dist-info/RECORD
