Metadata-Version: 2.1
Name: zltask
Version: 1.2.51
Summary: 深圳市筑龙科技的工作
Home-page: https://github.com/lanmengfei/testdm
Author: lanmengfei
Author-email: 865377886@qq.com
License: UNKNOWN
Platform: UNKNOWN
Classifier: Environment :: Web Environment
Classifier: Intended Audience :: Developers
Classifier: Operating System :: OS Independent
Classifier: Topic :: Text Processing :: Indexing
Classifier: Topic :: Utilities
Classifier: Topic :: Internet
Classifier: Topic :: Software Development :: Libraries :: Python Modules
Classifier: Programming Language :: Python
Classifier: Programming Language :: Python :: 3
Classifier: Programming Language :: Python :: 3.5
Requires-Dist: lmf (>=2.0.6)
